zope/componentvocabulary/__init__.py
zope/componentvocabulary/configure.zcml
zope/componentvocabulary/i18n.py
zope/componentvocabulary/vocabulary.py
zope/componentvocabulary/tests/__init__.py
zope/componentvocabulary/tests/test_configure.py
zope/componentvocabulary/tests/test_vocabulary.py
zope.componentvocabulary-4.0.dist-info/LICENSE.txt
zope.componentvocabulary-4.0.dist-info/METADATA
zope.componentvocabulary-4.0.dist-info/WHEEL
zope.componentvocabulary-4.0.dist-info/top_level.txt
zope.componentvocabulary-4.0.dist-info/RECORD
