Metadata-Version: 2.1
Name: zope.componentvocabulary
Version: 4.0
Summary: Component vocabularies
Home-page: http://github.com/zopefoundation/zope.componentvocabulary
Author: Zope Foundation and Contributors
Author-email: zope-dev@zope.dev
License: ZPL-2.1
Keywords: zope component architecture vocabulary
Classifier: Development Status :: 5 - Production/Stable
Classifier: Environment :: Web Environment
Classifier: Intended Audience :: Developers
Classifier: License :: OSI Approved :: Zope Public License
Classifier: Programming Language :: Python
Classifier: Programming Language :: Python :: 3
Classifier: Programming Language :: Python :: 3.9
Classifier: Programming Language :: Python :: 3.10
Classifier: Programming Language :: Python :: 3.11
Classifier: Programming Language :: Python :: 3.12
Classifier: Programming Language :: Python :: 3.13
Classifier: Programming Language :: Python :: Implementation :: CPython
Classifier: Programming Language :: Python :: Implementation :: PyPy
Classifier: Natural Language :: English
Classifier: Operating System :: OS Independent
Classifier: Topic :: Internet :: WWW/HTTP
Classifier: Framework :: Zope :: 3
Requires-Python: >=3.9
License-File: LICENSE.txt
Requires-Dist: setuptools
Requires-Dist: zope.component
Requires-Dist: zope.i18nmessageid
Requires-Dist: zope.interface
Requires-Dist: zope.schema
Requires-Dist: zope.security
Provides-Extra: test
Requires-Dist: zope.configuration; extra == "test"
Requires-Dist: zope.testing; extra == "test"
Requires-Dist: zope.testrunner>=6.4; extra == "test"
